setup.py
validater/__init__.py
validater/exceptions.py
validater/schema.py
validater/validaters.py
validater.egg-info/PKG-INFO
validater.egg-info/SOURCES.txt
validater.egg-info/dependency_links.txt
validater.egg-info/top_level.txt