Metadata-Version: 1.1
Name: validater
Version: 0.11.0
Summary: a python tool to validate json/dict/list and convert value by schema
Home-page: https://github.com/guyskk/validater
Author: guyskk
Author-email: guyskk@qq.com
License: MIT
Platform: UNKNOWN
Classifier: Intended Audience :: Developers
Classifier: License :: OSI Approved :: MIT License
Classifier: Operating System :: OS Independent
Classifier: Programming Language :: Python :: 3 :: Only
Classifier: Topic :: Software Development :: Libraries :: Python Modules
